<?xml version="1.0" encoding="UTF-8"?>
<game
    name="Legend of the Five Rings LCG"
    id="bb0f02e7-2a6f-4ae3-84a2-c501b4176844"
    octgnVersion="3.1.284.0"
    version="0.0.1.0"
    scriptVersion="3.1.0.2"
    markersize="16"
    setsurl="https://tinyurl.com/mab3ars"
    gameurl="http://octgngames.com/l5r-lcg"
    authors="Intolerance"
    description="Legend of the Five Rings: The Card Game is a player-influenced LCG that sees two players take on the role of one of the seven Great Clans of Rokugan, vying for military and political control of the land while maintaining Rokugan society’s strict code of honor."
    tags="legend five rings l5r lcg ffg fantasy flight games"
    iconurl="http://i.imgur.com/PgP90M6.jpg">
  <scripts>
    <script src="scripts/actions.py"/>
  </scripts>
  <proxygen definitionsrc="proxygen/definition.xml"/>
  <card back="card/back.png" front="card/front.png" width="63" height="88">
    <property name="Clan" type="String" textKind="Enum"/>
    <property name="Type" type="String" textKind="Enum"/>
    <property name="Unique" type="String"/>
    <property name="Traits" type="String" textKind="Tokens"/>
    <property name="Text" type="String"/>
    <property name="Cost" type="String"/>
    <property name="Military Skill" type="String"/>
    <property name="Political Skill" type="String"/>
    <property name="Glory" type="String"/>
    <property name="Bonus Strength" type="String"/>
    <property name="Starting Honor" type="String"/>
    <property name="Fate Value" type="String"/>
    <property name="Influence Value" type="String"/>
    <property name="Bonus Military Skill" type="String"/>
    <property name="Bonus Political Skill" type="String"/>
    <property name="Ring" type="String"/>
    <property name="Card Number" type="Integer"/>
    <size name="dynasty" back="card/dynasty.png" front="card/dynasty.png" width="63" height="88"/>
    <size name="conflict" back="card/conflict.png" front="card/conflict.png" width="63" height="88"/>
  </card>
  <table
    name="Table"
    width="1280"
    height="618"
    background="table/background.png"
    backgroundStyle="uniformToFill"
    ordered="False">
    <groupaction menu="Set up" execute="setup" showIf="setup_required"/>
    <cardaction menu="Default" execute="table_default_card_action" default="True" showIf="lambda: False"/>
    <cardaction menu="Bow/ready" execute="toggle_bow_ready"/>
    <cardaction menu="Discard" execute="discard"/>
    <cardaction menu="Flip" execute="flip"/>
    <cardaction menu="Play" execute="play_dynasty"/>
    <!--cardaction menu="Add fate" execute="add_fate" showIf="is_character"/-->
    <!--cardaction menu="Remove fate" execute="add_fate" showIf="is_character"/-->
  </table>
  <player>
    <globalvariable name="setup_required" value="True"/>
    <counter name="Honor" icon="icons/honor.png"/>
    <counter name="Fate" icon="icons/fate.png"/>
    <hand name="Hand" icon="card/conflict.png" visibility="me" ordered="False" width="63" height="88">
      <groupaction menu="Set up" execute="setup" showIf="setup_required"/>
      <groupaction menu="Random discard" execute="random_discard_from" showIf="setup_not_required"/>
      <cardaction menu="Play" execute="play_conflict" default="True" showIf="setup_not_required"/>
    </hand>
    <group name="Dynasty Deck" icon="card/dynasty.png" visibility="none" width="63" height="88"/>
    <group name="Dynasty Discard" icon="card/dynasty.png" visibility="all" width="63" height="88"/>
    <group name="Conflict Deck" icon="card/conflict.png" visibility="none" width="63" height="88"/>
    <group name="Conflict Discard" icon="card/conflict.png" visibility="all" width="63" height="88"/>
  </player>
  <deck>
    <section name="Stronghold" group="Hand"/>
    <section name="Province Cards" group="Hand"/>
    <section name="Dynasty Deck" group="Dynasty Deck"/>
    <section name="Conflict Deck" group="Conflict Deck"/>
  </deck>
</game>
